{"_id":{"$oid":"55903c673920390300af45f6"},"titulo":"La Torresaviñán","autor":"Nico 73","cloudinaryId":"subexpuesta/malej2cnybilk8vi9koz","acceso":"En coche por pista de tierra muy inclinada. No recomendable si ha llovido.","peligrosidad":5,"contaminacionLuminica":2,"latitud":40.977500537234064,"longitud":-2.5897908210754395,"direccion":"19268 Torremocha del Campo (Guadalajara), España","estado":0,"tags":["A2-Guadalajara","Torre"],"votos":0,"fechaToma":{"$date":"2014-02-12T23:00:00.000Z"},"__v":0,"loc":{"type":"Point","coordinates":[-2.5897908210754395,40.977500537234064]},"updatedAt":{"$date":"2020-08-22T21:55:24.023Z"},"ciudad":"Torremocha del Campo","codigoPostal":"19268","comunidad":"Castilla-La Mancha","pais":"ESP","provincia":"Guadalajara","createdAt":{"$date":"2015-06-28T18:26:47.018Z"},"visitas":60}