{"_id":{"$oid":"559ebdf84062e40300ba2679"},"titulo":"Paredon de San Telmo","autor":"josemlanza","cloudinaryId":"subexpuesta/j6r4tyisfgktlzrwiyke","acceso":"Llegamos hasta el aparcamiento de la playa de Santa Justa, y posteriormente tenemos que andar por un camino costero unos 1000m.","peligrosidad":1,"contaminacionLuminica":4,"latitud":43.42622964483041,"longitud":-4.097675085067749,"direccion":"39360 Santillana del Mar (Cantabria), España","estado":0,"tags":["Estructura"],"votos":0,"fechaToma":{"$date":"2015-01-23T23:00:00.000Z"},"__v":0,"loc":{"type":"Point","coordinates":[-4.097675085067749,43.42622964483041]},"updatedAt":{"$date":"2020-06-18T11:17:59.496Z"},"ciudad":"Santillana del Mar","codigoPostal":"39360","comunidad":"Cantabria","pais":"ESP","provincia":"Cantabria","createdAt":{"$date":"2015-07-09T18:31:20.797Z"},"visitas":27}