{"_id":{"$oid":"564eefe08df6270300803152"},"titulo":"El monolito de Alisas","autor":"jmmpereda","cloudinaryId":"subexpuesta/liwsucy25u7a7ltmzxr4","acceso":"Se puede llegar hasta el mirador en coche, hasta el monolito son unos 4-5 minutos andando, es una zona con buen cielo al Sur y solemos ir bastante para temas de Astrofotografía al ser un sitio alto y cómodo","peligrosidad":2,"contaminacionLuminica":4,"notasAdicionales":"En la foto el cometa C/2014 Q2 Lovejoy (el punto verde) e iluminado con la luz de la luna","latitud":43.300491556407394,"longitud":-3.6502115428447723,"estado":0,"categoria":0,"tags":["El-monolito-de-Alisas","Puerto-de-Alisas","Alisas","C/2014-Q2-Lovejoy","Lovejoy","Cometa"],"votos":0,"fechaToma":{"$date":"2014-12-28T23:00:00.000Z"},"__v":0,"loc":{"type":"Point","coordinates":[-3.6502115428447723,43.300491556407394]},"updatedAt":{"$date":"2020-07-18T06:06:39.572Z"},"ciudad":"Arredondo","codigoPostal":"39813","comunidad":"Cantabria","direccion":"39813 Arredondo (Cantabria), España","pais":"ESP","provincia":"Cantabria","createdAt":{"$date":"2015-11-20T10:03:12.440Z"},"visitas":38}