{"_id":{"$oid":"564ef81b8df6270300803157"},"titulo":"Mirador fuente del Chivo","autor":"jmmpereda","cloudinaryId":"subexpuesta/xl8dliw7qpwfleyltxhs","acceso":"Si no hay nieve se puede llegar en coche hasta el aparcamiento de arriba a 2.000 metros de altitud, buen cielo al Norte aunque es difícil acertar la noche a subir, normalmente mucho viento o niebla, aunque ayuda poder planificar gracias a la webcam de la estación de ski de Alto Campoo","peligrosidad":3,"contaminacionLuminica":5,"notasAdicionales":"En la foto dos débiles destellos de la lluvia de estrellas de finales de Julio, las Delta acuáridas","latitud":43.04521313586904,"longitud":-4.393683671951294,"estado":0,"categoria":0,"tags":["Mirador-fuente-del-Chivo","Alto-Campoo","Estación-de-ski"],"votos":0,"fechaToma":{"$date":"2014-07-31T22:00:00.000Z"},"__v":0,"loc":{"type":"Point","coordinates":[-4.393683671951294,43.04521313586904]},"updatedAt":{"$date":"2020-08-25T20:04:52.719Z"},"ciudad":"Hermandad de Campoo de Suso","codigoPostal":"39210","comunidad":"Cantabria","direccion":"CA-916, 39210 Hermandad de Campoo de Suso (Cantabria), España","pais":"ESP","provincia":"Cantabria","createdAt":{"$date":"2015-11-20T10:38:19.261Z"},"visitas":63}