{"_id":{"$oid":"566b2f9d85d71e03003498a9"},"titulo":"Búnker de la Guerra Civil","autor":"JuanmaMolina","cloudinaryId":"subexpuesta/o4hloc7jn0hds5ncmyij","acceso":"Se llega sin problemas por la autovía. Hay que coger un desvío y en dos minutos estás en el búnker. Para aparcar es más delicado, hay que dejar el coche en el arcén que no es muy ancho, aunque no es una carretera demasiado transitada.","peligrosidad":3,"contaminacionLuminica":5,"notasAdicionales":"No hay contaminación lumínica reseñable, aunque pasa cerca la autovía y hay algunas luces parásitas que es probable que se nos metan en el encuadre.\nHay que tener cuidado con las madrigueras en el búnker, ya que es muy fácil meter una pierna en una sin darnos cuenta y caernos.","latitud":37.79883724510842,"longitud":-1.3713517785072327,"estado":0,"categoria":4,"tags":["bunker","guerra-civil","murcia","abandono","ruina","nikon"],"votos":0,"fechaToma":{"$date":"2014-12-12T23:00:00.000Z"},"__v":0,"loc":{"type":"Point","coordinates":[-1.3713517785072327,37.79883724510842]},"updatedAt":{"$date":"2020-08-06T19:11:51.536Z"},"ciudad":"Alhama de Murcia","codigoPostal":"30849","comunidad":"Región de Murcia","direccion":"30849 Alhama de Murcia (Murcia), España","pais":"ESP","provincia":"Murcia","createdAt":{"$date":"2015-12-11T20:18:37.221Z"},"visitas":44}