{"_id":{"$oid":"5684f8d23e06310300db04d4"},"titulo":"PCTCAN","autor":"josemlanza","cloudinaryId":"subexpuesta/adn8o8lxjcw1ctedqrvu","acceso":"Sin problemas","peligrosidad":5,"contaminacionLuminica":5,"latitud":43.4539703303869,"longitud":-3.8720744848251343,"estado":0,"categoria":1,"tags":["Cantabria"],"votos":0,"fechaToma":{"$date":"2015-12-29T23:00:00.000Z"},"__v":0,"loc":{"type":"Point","coordinates":[-3.8720744848251343,43.4539703303869]},"updatedAt":{"$date":"2020-07-29T23:50:39.767Z"},"ciudad":"Santander","codigoPostal":"39011","comunidad":"Cantabria","direccion":"Avenida Severo Ochoa, 39011 Santander (Cantabria), España","pais":"ESP","provincia":"Cantabria","createdAt":{"$date":"2015-12-31T09:43:46.315Z"},"visitas":15}