{"_id":{"$oid":"5755423cce7c7f0300e33063"},"titulo":"Cap Blanc","autor":"joaquinain","cloudinaryId":"subexpuesta/qa60j1p12poquowqpdsk","acceso":"Díficil acceso. Esta cala se encuentra tras buscar una escalera empinada enclavada en una urbanización de chalets un tanto escondido. El terreno es muy irregular, ya que es un manto de rocas desprendidas de las paredes del acantilado, y es muy fácil pisar mal, torcerse un tobillo y acabar el día o la noche mal. Incluso plantar el trípode es costoso.","peligrosidad":7,"contaminacionLuminica":9,"notasAdicionales":"Es una zona eminentemente urbana, y los encuadres incluyen poblaciones, por lo que la contaminación lumínica es muy elevada.","latitud":38.67429501591656,"longitud":0.11339306831359863,"estado":0,"categoria":0,"tags":[],"votos":0,"fechaToma":{"$date":"2016-05-19T22:00:00.000Z"},"__v":0,"direccion":"Calle Cabo de Gata, 46, 03724 Teulada (Alicante), Espanya","loc":{"type":"Point","coordinates":[0.11339306831359863,38.67429501591656]},"updatedAt":{"$date":"2020-09-06T14:01:35.114Z"},"ciudad":"Teulada","codigoPostal":"03724","comunidad":"Comunidad Valenciana","pais":"ESP","provincia":"Alicante","createdAt":{"$date":"2016-06-06T09:28:28.018Z"},"visitas":46}