{"_id":{"$oid":"5778d62e1e32c203002bd061"},"titulo":"Arena","autor":"AntonioAliaga","cloudinaryId":"subexpuesta/rn6zv2yzbtywerijssa9","acceso":"Solo a pie tenemos que andar bastante entre 30 y 45 minutos por la playa el sendero es muy fácil.","peligrosidad":1,"contaminacionLuminica":7,"notasAdicionales":"En época estival la zona está llena de mosquitos llevar repelente , zona de muy fácil acceso es todo llano. Solo se puede andar por la costa no debemos salirnos de la zona ya que es zona protegida.","latitud":40.790494279876015,"longitud":0.7440876960754395,"codigoReto":"fa18","nombreReto":"Mapa de Faros de España","direccion":"43580 Deltebre (Tarragona), Espanya","estado":0,"categoria":0,"tags":[],"votos":0,"fechaToma":{"$date":"2015-09-05T22:00:00.000Z"},"__v":0,"loc":{"type":"Point","coordinates":[0.7440876960754395,40.790494279876015]},"updatedAt":{"$date":"2020-09-04T11:15:26.957Z"},"ciudad":"Deltebre","codigoPostal":"43580","comunidad":"Catalunya","pais":"ESP","provincia":"Tarragona","createdAt":{"$date":"2016-07-03T09:09:02.390Z"},"visitas":49}