{"_id":{"$oid":"577dfa9e746b8703007b52db"},"titulo":"Cabo Prior","autor":"Carlos Nikonista","cloudinaryId":"subexpuesta/urmwzotva3vbj3wq2pp0","acceso":"Se llega en coche.","peligrosidad":5,"contaminacionLuminica":5,"latitud":43.55417159337633,"longitud":-8.322830200195312,"codigoReto":"fa87","nombreReto":"","direccion":"Ferrol, 15594 Ferrol (A Coruña), España","estado":0,"categoria":0,"tags":[],"votos":0,"fechaToma":{"$date":"2013-07-22T22:00:00.000Z"},"__v":0,"loc":{"type":"Point","coordinates":[-8.322830200195312,43.55417159337633]},"updatedAt":{"$date":"2020-08-14T20:40:24.871Z"},"ciudad":"Ferrol","codigoPostal":"15594","comunidad":"Galicia","pais":"ESP","provincia":"A Coruña","createdAt":{"$date":"2016-07-07T06:45:50.018Z"},"visitas":28}