{"_id":{"$oid":"578cf41c1b1b4e03000334c6"},"titulo":"Ermita Virgen de la Guardia, Rocafort","autor":"kike-dc","cloudinaryId":"subexpuesta/bsqydppf7rdqlhctmoqn","acceso":"Se puede llegar en coche, pero mejor en 4x4 o coche un poco alto, un coche bajito podria rozcar los bajos varias veces .","peligrosidad":4,"contaminacionLuminica":4,"latitud":41.90310191824671,"longitud":0.3826814889907837,"codigoReto":"","nombreReto":"","direccion":"22512 San Esteban de Litera (Huesca), España","estado":0,"categoria":0,"tags":[],"votos":0,"fechaToma":{"$date":"2016-07-15T22:00:00.000Z"},"__v":0,"loc":{"type":"Point","coordinates":[0.3826814889907837,41.90310191824671]},"updatedAt":{"$date":"2020-09-04T14:47:38.753Z"},"ciudad":"San Esteban de Litera","codigoPostal":"22512","comunidad":"Aragón","pais":"ESP","provincia":"Huesca","createdAt":{"$date":"2016-07-18T15:22:04.375Z"},"visitas":65}