{"_id":{"$oid":"581bb6be98e93f03004f568c"},"titulo":"FARO LA GUIA","autor":"Eduardo martinez","cloudinaryId":"subexpuesta/otc37xoledxojegxnhg1","acceso":"Acceso por un paseo peatonal de muy fácil acceso. Se puede llegar en coche hasta escasos 100 ms del faro.","peligrosidad":3,"contaminacionLuminica":7,"latitud":42.25954485657418,"longitud":-8.702330589294434,"codigoReto":"fa72","nombreReto":"Mapa de Faros de España","direccion":"36207 Vigo (Pontevedra), España","estado":0,"categoria":0,"tags":[],"votos":0,"fechaToma":{"$date":"2016-11-02T23:00:00.000Z"},"__v":0,"loc":{"type":"Point","coordinates":[-8.702330589294434,42.25954485657418]},"updatedAt":{"$date":"2020-08-25T22:33:29.505Z"},"ciudad":"Vigo","codigoPostal":"36207","comunidad":"Galicia","pais":"ESP","provincia":"Pontevedra","createdAt":{"$date":"2016-11-03T22:14:22.494Z"},"visitas":43}