{"_id":{"$oid":"581c69925d33f503005947ce"},"titulo":"Molino estelear","autor":"dmaimo","cloudinaryId":"subexpuesta/alt8p44osq4xrn2saxww","acceso":"Se llega en coche, no hay ningún peligro","peligrosidad":5,"contaminacionLuminica":5,"notasAdicionales":"Mucha contaminación lumínica, el aeropuerto esta justo delante, aprovechamos que la pista esta en mantenimiento y tenía las luces apagadas.","latitud":39.562011169671266,"longitud":2.7781878411769867,"codigoReto":"","nombreReto":"","direccion":"07199 Palma (Illes Balears), Espanya","estado":0,"categoria":4,"tags":[],"votos":0,"fechaToma":{"$date":"2016-10-29T22:00:00.000Z"},"__v":0,"loc":{"type":"Point","coordinates":[2.7781878411769867,39.562011169671266]},"updatedAt":{"$date":"2020-08-14T16:32:25.391Z"},"ciudad":"Palma","codigoPostal":"07199","comunidad":"Illes Balears","pais":"ESP","provincia":"Illes Balears","createdAt":{"$date":"2016-11-04T10:57:22.127Z"},"visitas":30}