{"_id":{"$oid":"5895177bae3a4904000d1ae6"},"titulo":"Faro Cabo Mayor","autor":"seglion","cloudinaryId":"subexpuesta/q6y68wnsie5xly7krimb","acceso":"Se llega en coche facilmente. Solo se puede acceder hasta las 21:30","peligrosidad":1,"contaminacionLuminica":7,"latitud":43.49090520450164,"longitud":-3.7904997915029526,"codigoReto":"fa110","nombreReto":"Mapa de Faros de España","direccion":"39012 Santander (Cantabria), España","estado":0,"categoria":3,"tags":[],"votos":0,"fechaToma":{"$date":"2017-01-31T23:00:00.000Z"},"__v":0,"loc":{"type":"Point","coordinates":[-3.7904997915029526,43.49090520450164]},"updatedAt":{"$date":"2020-09-05T01:52:21.136Z"},"ciudad":"Santander","codigoPostal":"39012","comunidad":"Cantabria","pais":"ESP","provincia":"Cantabria","createdAt":{"$date":"2017-02-03T23:51:23.494Z"},"visitas":25}