{"_id":{"$oid":"5ca8f2696ade180013031952"},"loc":{"type":"Point","coordinates":[-3.650121688842774,40.416371399358034]},"categoria":1,"estado":0,"tags":["Nikon","d750","20mm1.8","Madrid","pirulí","estelas","sunset"],"votos":0,"visitas":33,"guardado":0,"filtros":[],"titulo":"Madrid puro nervio","autor":"invesado","cloudinaryId":"subexpuesta/ycztsp0sthelqxupaok6","acceso":"Se aparca bien frente al cementerio","peligrosidad":1,"contaminacionLuminica":10,"latitud":40.416371399358034,"longitud":-3.650121688842774,"altitud":"","marca":"","modelo":"","exif":{"marca":"Nikon","modelo":"d750","objetivo":"40mm","apertura":"7.1","velocidad":"25\"","iso":"400","balanceBlancos":"4750","fechaToma":"2019-03-29T23:00:00Z"},"direccion":"-","pais":"ESP","comunidad":"Comunidad de Madrid","provincia":"Madrid","ciudad":"Madrid","codigoPostal":"28017","fechaToma":{"$date":"2019-04-06T18:39:37.519Z"},"fechaSubida":{"$date":"2019-04-06T18:39:37.519Z"},"createdAt":{"$date":"2019-04-06T18:39:37.522Z"},"updatedAt":{"$date":"2020-07-25T17:19:34.156Z"},"__v":0}