{"_id":{"$oid":"5ddf9f8c2ea3c00013a53c4f"},"loc":{"coordinates":[-3.5328440615424177,40.49722868965843],"type":"Point"},"categoria":0,"estado":0,"tags":[],"votos":0,"visitas":27,"guardado":0,"filtros":[],"titulo":"La calma delante de la vorágine","autor":"felisuco71","cloudinaryId":"subexpuesta/vncvjd7pbyj4ikesxyxk","acceso":"Con coche hasta 100 metros antes del sitio, luego campo, mejor con luna nueva ojo es un barranco, cuidado con caídas.","peligrosidad":9,"contaminacionLuminica":7,"latitud":40.49722868965843,"longitud":-3.5328440615424177,"altitud":"","marca":"","modelo":"","exif":{"marca":"NIKON CORPORATION","modelo":"NIKON D500","objetivo":"150.0-500.0 mm f/5.0-6.3","apertura":"5.6","velocidad":"0.5","iso":"400","balanceBlancos":"4050","fechaToma":"2019-11-26T23:00:00Z"},"direccion":"-","pais":"ESP","comunidad":"Comunidad de Madrid","provincia":"Madrid","ciudad":"Paracuellos de Jarama","codigoPostal":"28860","fechaToma":{"$date":"2019-11-28T10:21:00.083Z"},"fechaSubida":{"$date":"2019-11-28T10:21:00.083Z"},"createdAt":{"$date":"2019-11-28T10:21:00.085Z"},"updatedAt":{"$date":"2020-08-27T03:04:09.353Z"},"__v":0}