{"_id":{"$oid":"5ead7b0a02ad880013bb9644"},"loc":{"coordinates":[-8.867887258529665,42.54239139584902],"type":"Point"},"categoria":7,"estado":0,"tags":[],"votos":0,"visitas":3,"guardado":0,"filtros":[],"titulo":"Ponte da Illa de Arousa o lonxe","autor":"Pedro González","cloudinaryId":"subexpuesta/d1z0rwoc8oyv7p3nrkb0","acceso":"Playa","peligrosidad":0,"contaminacionLuminica":0,"latitud":42.54239139584902,"longitud":-8.867887258529665,"altitud":"","marca":"","modelo":"","exif":{"marca":"NIKON CORPORATION","modelo":"NIKON D3200","objetivo":"18.0-55.0 mm f/3.5-5.6","apertura":"22.0","velocidad":"1/80","iso":"400","balanceBlancos":"","fechaToma":"2014-09-07T22:00:00Z"},"direccion":"-","pais":"ESP","comunidad":"Galicia","provincia":"Pontevedra","ciudad":"A Illa de Arousa","codigoPostal":"36626","fechaToma":{"$date":"2020-05-02T13:52:10.792Z"},"fechaSubida":{"$date":"2020-05-02T13:52:10.792Z"},"createdAt":{"$date":"2020-05-02T13:52:10.795Z"},"updatedAt":{"$date":"2020-08-07T10:49:33.641Z"},"__v":0}